MelodieStudio/__init__.py
MelodieStudio/__main__.py
MelodieStudio/_config.py
MelodieStudio/hotupdate.py
MelodieStudio/main.py
MelodieStudio/window.py
MelodieStudio/gateway/__init__.py
MelodieStudio/gateway/gateway.py
MelodieStudio/management/__init__.py
MelodieStudio/management/ast_parse.py
MelodieStudio/management/ast_unparse.py
MelodieStudio/management/codegen.py
MelodieStudio/management/dataflow.py
MelodieStudio/management/experiment_status.py
MelodieStudio/management/pil_gen.py
MelodieStudio/management/pos.py
MelodieStudio/management/project_structure.py
MelodieStudio/management/pycfg.py
MelodieStudio/management/run_cfg.py
MelodieStudio/manipulators/__init__.py
MelodieStudio/manipulators/base.py
MelodieStudio/manipulators/network_manipulator.py
MelodieStudio/manipulators/table_manipulator.py
MelodieStudio/manipulators/textfile_manipulator.py
MelodieStudio/models/__init__.py
MelodieStudio/models/messages.py
MelodieStudio/models/models.py
MelodieStudio/models/pty.py
MelodieStudio/routes/__init__.py
MelodieStudio/routes/charts.py
MelodieStudio/routes/db_browser.py
MelodieStudio/routes/filesystem.py
MelodieStudio/routes/lowcode.py
MelodieStudio/routes/tools.py
MelodieStudio/routes/utils.py
MelodieStudio/routes/visualizer.py
MelodieStudio/routes/wrapper.py
MelodieStudio/routes/ws.py
MelodieStudio/routes/files/__init__.py
MelodieStudio/routes/files/table_files/__init__.py
MelodieStudio/routes/files/table_files/conversions.py
MelodieStudio/routes/files/table_files/excel.py
MelodieStudio/services/json_config.py
MelodieStudio/static/car.png
MelodieStudio/static/favicon.ico
MelodieStudio/static/index.html
MelodieStudio/static/test_write.py
MelodieStudio/static/js/app.js
MelodieStudio/static/js/chunk-vendors.js
MelodieStudio/static/js/node_modules_core-js_modules_es_error_cause_js.js
MelodieStudio/static/js/node_modules_element-plus_es_components_dialog_index_mjs-node_modules_element-plus_es_compone-f8d42e.js
MelodieStudio-0.7.0.dist-info/METADATA
MelodieStudio-0.7.0.dist-info/WHEEL
MelodieStudio-0.7.0.dist-info/entry_points.txt
MelodieStudio-0.7.0.dist-info/top_level.txt
MelodieStudio-0.7.0.dist-info/RECORD
