Metadata-Version: 2.1
Name: MelodieStudio
Version: 0.7.0
Summary: A web-based toolbox for Melodie ABM package.
Home-page: https://github.com/ABM4ALL/MelodieStudio
Author: Songmin Yu, Zhanyi Hou
Author-email: abm4all@outlook.com
License: BSD 3
Platform: UNKNOWN
Classifier: Development Status :: 4 - Beta
Classifier: Intended Audience :: Science/Research
Classifier: License :: OSI Approved :: BSD License
Classifier: Natural Language :: English
Classifier: Operating System :: Unix
Classifier: Operating System :: Microsoft :: Windows
Classifier: Programming Language :: Python :: 3
Classifier: Topic :: Scientific/Engineering :: Artificial Intelligence
Requires-Python: >3.5
Requires-Dist: chardet
Requires-Dist: websockets
Requires-Dist: sqlalchemy
Requires-Dist: flask
Requires-Dist: flask-cors
Requires-Dist: astunparse
Requires-Dist: pprintast
Requires-Dist: psutil
Requires-Dist: watchdog
Requires-Dist: flask-sock
Requires-Dist: py-ts-interfaces
Requires-Dist: jedi
Requires-Dist: rpyc
Requires-Dist: websocket-client
Requires-Dist: brotli
Requires-Dist: pywinpty ; os_name == "nt"
